dh5cli/__init__.py
dh5cli/dh5tree.py
dh5io/__init__.py
dh5io/cont.py
dh5io/create.py
dh5io/dh5file.py
dh5io/dh5mne.py
dh5io/dhfun.py
dh5io/ensure_h5py_file.py
dh5io/errors.py
dh5io/event_triggers.py
dh5io/markers.py
dh5io/operations.py
dh5io/py.typed
dh5io/spike.py
dh5io/trialmap.py
dh5io/validation.py
dh5io/version.py
dh5io-0.2.1.dist-info/licenses/LICENSE
dh5neo/__init__.py
dh5neo/dh5neo.py
dh5neo/dh5rawio.py
dh5neo/exampleio.py
dh5neo/examplerawio.py
dhspec/__init__.py
dhspec/cont.py
dhspec/dh5file.py
dhspec/event_triggers.py
dhspec/intervals.py
dhspec/markers.py
dhspec/operations.py
dhspec/py.typed
dhspec/spike.py
dhspec/trialmap.py
dhzio/__init__.py
dhzio/cont.py
dhzio/dhzfile.py
dhzio/errors.py
dh5io-0.2.1.dist-info/METADATA
dh5io-0.2.1.dist-info/WHEEL
dh5io-0.2.1.dist-info/entry_points.txt
dh5io-0.2.1.dist-info/top_level.txt
dh5io-0.2.1.dist-info/RECORD
