Metadata-Version: 2.4
Name: dh5io
Version: 0.2.1
Summary: Python tools for DAQ-HDF5 (dh5) file format used at Brain Research Institute of University of Bremen
Author-email: Joscha Schmiedt <schmiedt@brain.uni-bremen.de>
License-Expression: MIT
Keywords: data format,electrophysiology,hdf5,daq
Classifier: Development Status :: 3 - Alpha
Classifier: Intended Audience :: Science/Research
Classifier: Operating System :: OS Independent
Classifier: Programming Language :: Python :: 3
Classifier: Programming Language :: Python :: 3.11
Classifier: Programming Language :: Python :: 3.12
Classifier: Programming Language :: Python :: 3.13
Classifier: Topic :: Scientific/Engineering
Classifier: Topic :: Software Development :: Libraries :: Python Modules
Requires-Python: >=3.11
License-File: LICENSE
Requires-Dist: numpy
Requires-Dist: h5py
Provides-Extra: dev
Requires-Dist: ipykernel>=6.29.5; extra == "dev"
Requires-Dist: ipython>=9.0.2; extra == "dev"
Requires-Dist: mypy>=1.15.0; extra == "dev"
Requires-Dist: ruff>=0.11.2; extra == "dev"
Requires-Dist: dh5io[all]; extra == "dev"
Provides-Extra: dhzio
Requires-Dist: zarr>=3.0.6; extra == "dhzio"
Provides-Extra: all
Requires-Dist: dh5io[test]; extra == "all"
Requires-Dist: dh5io[neo]; extra == "all"
Requires-Dist: dh5io[dhzio]; extra == "all"
Provides-Extra: neo
Requires-Dist: neo; extra == "neo"
Provides-Extra: test
Requires-Dist: pytest; extra == "test"
Requires-Dist: pytest-cov; extra == "test"
Requires-Dist: dh5io[neo]; extra == "test"
Requires-Dist: dh5io[dhzio]; extra == "test"
Dynamic: license-file
